{
	"format_version": "1.8.0",
	"animations": {
		"animation.technopig.baby_transform": {
			"loop": true,
			"bones": {
				"head": {
					"position": [0, 4, 4],
					"scale": 2
				}
			}
		},
		"animation.technopig.setup": {
			"loop": true,
			"bones": {
				"body": {
					"rotation": ["-this", 0, 0]
				}
			}
		},
		"animation.technopig.walk": {
			"loop": true,
			"animation_length": 1,
			"anim_time_update": "query.modified_distance_moved",
			"bones": {
				"leg1": {
					"rotation": {
						"0.0": {
							"post": {
								"vector": [-38.17, 0, 0]
							},
							"lerp_mode": "catmullrom"
						},
						"0.5": {
							"post": {
								"vector": [38.17, 0, 0]
							},
							"lerp_mode": "catmullrom"
						},
						"1.0": {
							"post": {
								"vector": [-38.17, 0, 0]
							},
							"lerp_mode": "catmullrom"
						}
					}
				},
				"leg2": {
					"rotation": {
						"0.0": {
							"post": {
								"vector": [38.17, 0, 0]
							},
							"lerp_mode": "catmullrom"
						},
						"0.5": {
							"post": {
								"vector": [-38.17, 0, 0]
							},
							"lerp_mode": "catmullrom"
						},
						"1.0": {
							"post": {
								"vector": [38.17, 0, 0]
							},
							"lerp_mode": "catmullrom"
						}
					}
				},
				"leg3": {
					"rotation": {
						"0.0": {
							"post": {
								"vector": [-38.17, 0, 0]
							},
							"lerp_mode": "catmullrom"
						},
						"0.5": {
							"post": {
								"vector": [38.17, 0, 0]
							},
							"lerp_mode": "catmullrom"
						},
						"1.0": {
							"post": {
								"vector": [-38.17, 0, 0]
							},
							"lerp_mode": "catmullrom"
						}
					}
				},
				"leg4": {
					"rotation": {
						"0.0": {
							"post": {
								"vector": [38.17, 0, 0]
							},
							"lerp_mode": "catmullrom"
						},
						"0.5": {
							"post": {
								"vector": [-38.17, 0, 0]
							},
							"lerp_mode": "catmullrom"
						},
						"1.0": {
							"post": {
								"vector": [38.17, 0, 0]
							},
							"lerp_mode": "catmullrom"
						}
					}
				}
			}
		}
	}
}